odoo8_addon_web_sheet_full_width_selective-8.0.0.1.0-py2.7-nspkg.pth
odoo8_addon_web_sheet_full_width_selective-8.0.0.1.0.dist-info/top_level.txt
odoo8_addon_web_sheet_full_width_selective-8.0.0.1.0.dist-info/WHEEL
odoo8_addon_web_sheet_full_width_selective-8.0.0.1.0.dist-info/RECORD
odoo8_addon_web_sheet_full_width_selective-8.0.0.1.0.dist-info/metadata.json
odoo8_addon_web_sheet_full_width_selective-8.0.0.1.0.dist-info/DESCRIPTION.rst
odoo8_addon_web_sheet_full_width_selective-8.0.0.1.0.dist-info/METADATA
odoo8_addon_web_sheet_full_width_selective-8.0.0.1.0.dist-info/namespace_packages.txt
odoo_addons/web_sheet_full_width_selective/__openerp__.py
odoo_addons/web_sheet_full_width_selective/__init__.py
odoo_addons/web_sheet_full_width_selective/README.rst
odoo_addons/web_sheet_full_width_selective/views/sheet.xml
odoo_addons/web_sheet_full_width_selective/static/description/icon.png
odoo_addons/web_sheet_full_width_selective/static/src/css/sheet.css
